{
  "estimated_hlj_count": 8,
  "chunk_count": 1,
  "chunks": [
    {
      "chunk_id": "REQ-025-HLJ-Chunk_1",
      "focus": "Widget Performance Analytics",
      "items": [
        {
          "id": "REQ-025-HLJ-Chunk_1-Item_1-v1.0",
          "title": "Instrument dashboard widgets for load and render times",
          "domain": "SaaS",
          "subdomain": [
            "Performance Analytics"
          ],
          "tags": [
            "instrumentation",
            "performance"
          ],
          "difficulty": "medium",
          "priority": "high",
          "line_source": "Ln 10-13"
        },
        {
          "id": "REQ-025-HLJ-Chunk_1-Item_2-v1.0",
          "title": "Report timing data per widget instance, user, device, and browser context",
          "domain": "SaaS",
          "subdomain": [
            "Performance Analytics"
          ],
          "tags": [
            "reporting",
            "analytics"
          ],
          "difficulty": "medium",
          "priority": "high",
          "line_source": "Ln 14-15"
        },
        {
          "id": "REQ-025-HLJ-Chunk_1-Item_3-v1.0",
          "title": "Provide engineering dashboards with breakdowns by widget, user segment, and time window",
          "domain": "SaaS",
          "subdomain": [
            "Visualization"
          ],
          "tags": [
            "visualization",
            "dashboards"
          ],
          "difficulty": "medium",
          "priority": "high",
          "line_source": "Ln 16-17"
        },
        {
          "id": "REQ-025-HLJ-Chunk_1-Item_4-v1.0",
          "title": "Flag outliers and regressions, with drill-down to root cause",
          "domain": "SaaS",
          "subdomain": [
            "Performance Analytics"
          ],
          "tags": [
            "alerting",
            " Root Cause Analysis"
          ],
          "difficulty": "high",
          "priority": "high",
          "line_source": "Ln 18-19"
        },
        {
          "id": "REQ-025-HLJ-Chunk_1-Item_5-v1.0",
          "title": "Trigger alerts for widgets breaching performance SLAs",
          "domain": "SaaS",
          "subdomain": [
            "Automated Alerting"
          ],
          "tags": [
            "alerting",
            "SLA"
          ],
          "difficulty": "medium",
          "priority": "high",
          "line_source": "Ln 20-21"
        },
        {
          "id": "REQ-025-HLJ-Chunk_1-Item_6-v1.0",
          "title": "Integrate with CI/CD to block deployment of code that causes performance regressions",
          "domain": "SaaS",
          "subdomain": [
            "Automated Optimization"
          ],
          "tags": [
            "CI/CD",
            "optimization"
          ],
          "difficulty": "high",
          "priority": "high",
          "line_source": "Ln 22-23"
        },
        {
          "id": "REQ-025-HLJ-Chunk_1-Item_7-v1.0",
          "title": "Monitor fallback performance and alert on persistent issues for widgets loading from external services",
          "domain": "SaaS",
          "subdomain": [
            "Edge Cases"
          ],
          "tags": [
            "fallback",
            "external services"
          ],
          "difficulty": "medium",
          "priority": "medium",
          "line_source": "Ln 24-25"
        },
        {
          "id": "REQ-025-HLJ-Chunk_1-Item_8-v1.0",
          "title": "Anonymize telemetry data and comply with user privacy agreements",
          "domain": "SaaS",
          "subdomain": [
            "Compliance"
          ],
          "tags": [
            "privacy",
            "compliance"
          ],
          "difficulty": "high",
          "priority": "high",
          "line_source": "Ln 26-27"
        }
      ]
    }
  ]
}