{
  "hlj_id": "REQ-023-HLJ-Chunk_2-Item_7-v1.0",
  "model": "opus4",
  "req_id": "req-023",
  "domain": "SaaS",
  "title": "Maintain comprehensive change log for all flag adjustments and rollbacks",
  "summary": "Implement persistent change logging system capturing all feature flag modifications, rollbacks, and configuration changes. Must support compliance audits and provide queryable history for analysis.",
  "tags_v1": [
    "audit",
    "compliance",
    "backend"
  ],
  "tags_v2": [
    "audit",
    "compliance"
  ],
  "tags_v3": [
    "audit",
    "compliance",
    "real-time-analytics",
    "monitoring",
    "alert"
  ],
  "all_tag_metadata": [
    {
      "tag": "audit",
      "aliases": [
        "auditability"
      ],
      "cluster_id": "all_25",
      "domains": [
        "FinTech",
        "SaaS"
      ],
      "model": "opus4",
      "version": "tags_v1",
      "score": 2,
      "confidence": 0.7376808524131775,
      "validated": true,
      "validation_reason": "similarity_above_threshold",
      "original_tag": "audit",
      "method": "dedup_canonical"
    },
    {
      "tag": "compliance",
      "aliases": [
        "compliancereporting",
        "compliance monitoring"
      ],
      "cluster_id": "all_12",
      "domains": [
        "Compliance and Security",
        "FinTech",
        "SaaS",
        "Security"
      ],
      "model": "opus4",
      "version": "tags_v1",
      "score": 2,
      "confidence": 0.7239878177642822,
      "validated": true,
      "validation_reason": "similarity_above_threshold",
      "original_tag": "compliance",
      "method": "dedup_canonical"
    },
    {
      "tag": "real-time-analytics",
      "aliases": [
        "real-time analytics",
        "real-time monitoring"
      ],
      "cluster_id": "all_141",
      "domains": [
        "SaaS"
      ],
      "model": "meta70b",
      "version": "tags_v1",
      "score": 2,
      "confidence": 0.7937229871749878,
      "validated": true,
      "validation_reason": "similarity_above_threshold",
      "original_tag": "real-time analytics",
      "method": "dedup_canonical"
    },
    {
      "tag": "monitoring",
      "aliases": [],
      "cluster_id": "all_23",
      "domains": [
        "FinTech",
        "SaaS"
      ],
      "model": "meta70b",
      "version": "tags_v1",
      "score": 1,
      "confidence": 0.7511683106422424,
      "validated": true,
      "validation_reason": "similarity_above_threshold",
      "original_tag": "monitoring",
      "method": "dedup_canonical"
    },
    {
      "tag": "alert",
      "aliases": [
        "alerting",
        "alerts"
      ],
      "cluster_id": "all_53",
      "domains": [
        "FinTech",
        "SaaS"
      ],
      "model": "meta70b",
      "version": "tags_v1",
      "score": 1,
      "confidence": 0.7052798271179199,
      "validated": true,
      "validation_reason": "similarity_above_threshold",
      "original_tag": "alerts",
      "method": "dedup_canonical"
    }
  ]
}